{
  "${ModID}:Mojo": {
    "NAME": "Mojo",
    "DESCRIPTIONS": [
      "Increases non-attack damage by #b",
      "."
    ]
  },
  "${ModID}:Maledict": {
    "NAME": "Maledict",
    "DESCRIPTIONS": [
      "Receives #b",
      "% more non-attack damage for #b",
      " turn.",
      " turns."
    ]
  },
  "${ModID}:Spines": {
    "NAME": "Spines",
    "DESCRIPTIONS": [
      "Whenever an enemy performs a non-attack action, they take #b",
      " damage."
    ]
  },
  "${ModID}:Venom": {
    "NAME": "Venom",
    "DESCRIPTIONS": [
      "For #b",
      " turn, whenever this enemy takes damage, it loses #b1 HP.",
      " turns, whenever this enemy takes damage, it loses #b1 HP."
    ]
  }
}
